component_deployer/__init__.py
component_deployer/__main__.py
component_deployer/utils.py
component_deployer-0.9.1.8.dist-info/DESCRIPTION.rst
component_deployer-0.9.1.8.dist-info/METADATA
component_deployer-0.9.1.8.dist-info/RECORD
component_deployer-0.9.1.8.dist-info/WHEEL
component_deployer-0.9.1.8.dist-info/entry_points.txt
component_deployer-0.9.1.8.dist-info/metadata.json
component_deployer-0.9.1.8.dist-info/top_level.txt
